txl_notebook_viewer/__init__.py
txl_notebook_viewer/components.py
txl_notebook_viewer-0.1.17.dist-info/METADATA
txl_notebook_viewer-0.1.17.dist-info/WHEEL
txl_notebook_viewer-0.1.17.dist-info/entry_points.txt
txl_notebook_viewer-0.1.17.dist-info/licenses/LICENSE.txt
txl_notebook_viewer-0.1.17.dist-info/RECORD
