Metadata-Version: 2.1
Name: txl_notebook_viewer
Version: 0.1.17
Summary: TXL plugin for a notebook viewer
Project-URL: Source, https://github.com/davidbrochart/jpterm/plugins/notebook_viewer
Author-email: David Brochart <david.brochart@gmail.com>
License-Expression: MIT
License-File: LICENSE.txt
Classifier: Development Status :: 4 - Beta
Classifier: Programming Language :: Python
Classifier: Programming Language :: Python :: 3.10
Classifier: Programming Language :: Python :: 3.11
Classifier: Programming Language :: Python :: Implementation :: CPython
Classifier: Programming Language :: Python :: Implementation :: PyPy
Requires-Python: >=3.10
Requires-Dist: txl
